fastapi_depends_stub/__init__.py
fastapi_depends_stub/stub.py
fastapi_depends_stub-1.0.0.dist-info/LICENSE
fastapi_depends_stub-1.0.0.dist-info/WHEEL
fastapi_depends_stub-1.0.0.dist-info/METADATA
fastapi_depends_stub-1.0.0.dist-info/RECORD
