Metadata-Version: 2.1
Name: fastapi-depends-stub
Version: 1.0.0
Summary: Prevent FastAPI from digging into real dependencies attributes detecting them as request data.
Author: Timur Kasimov
Author-email: tkasimov@icloud.com
Requires-Python: >=3.9,<4.0
Classifier: Programming Language :: Python :: 3
Classifier: Programming Language :: Python :: 3.10
Classifier: Programming Language :: Python :: 3.9
